gdevtools/__init__.py
gdevtools/cli.py
gdevtools/apis/__init__.py
gdevtools/apis/gitlab/__init__.py
gdevtools/apis/gitlab/client.py
gdevtools/apis/gitlab/groups.py
gdevtools/apis/gitlab/projects.py
gdevtools/apis/gitlab/types.py
gdevtools/commands/__init__.py
gdevtools/commands/gitlab/__init__.py
gdevtools/commands/gitlab/variables.py
gdevtools-0.1.0.dist-info/METADATA
gdevtools-0.1.0.dist-info/WHEEL
gdevtools-0.1.0.dist-info/entry_points.txt
gdevtools-0.1.0.dist-info/RECORD
