Metadata-Version: 2.4
Name: gdevtools
Version: 0.1.0
Summary: Common developer utilities for local development
Requires-Python: >=3.12
Requires-Dist: httpx>=0.28.1
Requires-Dist: pydantic>=2.11.5
Requires-Dist: typer>=0.16.0
